pyoxynet/__init__.py
pyoxynet/model.py
pyoxynet/testing.py
pyoxynet/utilities.py
pyoxynet/AIS/__init__.py
pyoxynet/AIS/keras_metadata.pb
pyoxynet/AIS/saved_model.pb
pyoxynet/AIS/variables.data-00000-of-00001
pyoxynet/AIS/variables.index
pyoxynet/LSTMGRUModel/__init__.py
pyoxynet/LSTMGRUModel/keras_metadata.pb
pyoxynet/LSTMGRUModel/saved_model.pb
pyoxynet/LSTMGRUModel/variables.data-00000-of-00001
pyoxynet/LSTMGRUModel/variables.index
pyoxynet/NSWIS/__init__.py
pyoxynet/NSWIS/keras_metadata.pb
pyoxynet/NSWIS/saved_model.pb
pyoxynet/NSWIS/variables.data-00000-of-00001
pyoxynet/NSWIS/variables.index
pyoxynet/TCN/__init__.py
pyoxynet/TCN/keras_metadata.pb
pyoxynet/TCN/saved_model.pb
pyoxynet/TCN/variables.data-00000-of-00001
pyoxynet/TCN/variables.index
pyoxynet/data_test/__init__.py
pyoxynet/data_test/data_test.csv
pyoxynet/data_test/database_statistics_ramp.csv
pyoxynet/data_test/database_statistics_resting.csv
pyoxynet/data_test/ramp_real_test_1.csv
pyoxynet/data_test/ramp_real_test_10.csv
pyoxynet/data_test/ramp_real_test_11.csv
pyoxynet/data_test/ramp_real_test_12.csv
pyoxynet/data_test/ramp_real_test_13.csv
pyoxynet/data_test/ramp_real_test_14.csv
pyoxynet/data_test/ramp_real_test_15.csv
pyoxynet/data_test/ramp_real_test_16.csv
pyoxynet/data_test/ramp_real_test_17.csv
pyoxynet/data_test/ramp_real_test_18.csv
pyoxynet/data_test/ramp_real_test_19.csv
pyoxynet/data_test/ramp_real_test_2.csv
pyoxynet/data_test/ramp_real_test_20.csv
pyoxynet/data_test/ramp_real_test_21.csv
pyoxynet/data_test/ramp_real_test_22.csv
pyoxynet/data_test/ramp_real_test_23.csv
pyoxynet/data_test/ramp_real_test_24.csv
pyoxynet/data_test/ramp_real_test_25.csv
pyoxynet/data_test/ramp_real_test_26.csv
pyoxynet/data_test/ramp_real_test_27.csv
pyoxynet/data_test/ramp_real_test_28.csv
pyoxynet/data_test/ramp_real_test_29.csv
pyoxynet/data_test/ramp_real_test_3.csv
pyoxynet/data_test/ramp_real_test_30.csv
pyoxynet/data_test/ramp_real_test_31.csv
pyoxynet/data_test/ramp_real_test_32.csv
pyoxynet-0.1.12.dist-info/licenses/LICENSE.txt
pyoxynet-0.1.12.dist-info/METADATA
pyoxynet-0.1.12.dist-info/WHEEL
pyoxynet-0.1.12.dist-info/top_level.txt
pyoxynet-0.1.12.dist-info/RECORD
