Metadata-Version: 2.4
Name: pyoxynet
Version: 0.1.12
Summary: Python package of the Oxynet project
Author: Andrea Zignoli
Author-email: andrea.zignoli@unitn.it
Classifier: Programming Language :: Python :: 3.10
Classifier: License :: OSI Approved :: MIT License
Classifier: Operating System :: OS Independent
Requires-Python: >=3.10
License-File: LICENSE.txt
Requires-Dist: importlib-resources
Requires-Dist: pandas
Requires-Dist: uniplot
Requires-Dist: scipy
Requires-Dist: chardet
Requires-Dist: xlrd
Requires-Dist: openpyxl
Requires-Dist: matplotlib
Provides-Extra: full
Requires-Dist: tensorflow; extra == "full"
Requires-Dist: shap; extra == "full"
Provides-Extra: tflite
Requires-Dist: tflite-runtime; extra == "tflite"
Dynamic: author
Dynamic: author-email
Dynamic: classifier
Dynamic: description
Dynamic: description-content-type
Dynamic: license-file
Dynamic: provides-extra
Dynamic: requires-dist
Dynamic: requires-python
Dynamic: summary
